sheetsandbox/__init__.py
sheetsandbox/client.py
sheetsandbox/utils.py
sheetsandbox-1.0.2.dist-info/METADATA
sheetsandbox-1.0.2.dist-info/WHEEL
sheetsandbox-1.0.2.dist-info/top_level.txt
sheetsandbox-1.0.2.dist-info/RECORD
