Metadata-Version: 2.4
Name: sheetsandbox
Version: 1.0.2
Summary: Add your description here
Home-page: https://github.com/sheetsandbox/sheetsandbox-pip
Author: Aravind Kumar Vemula
Author-email: 30lmas09@gmail.com
Requires-Python: >=3.7
Dynamic: author
Dynamic: author-email
Dynamic: home-page
Dynamic: requires-python
